setup.py
alengen/__init__.py
alengen/codegen.py
alengen/main.py
alengen.egg-info/PKG-INFO
alengen.egg-info/SOURCES.txt
alengen.egg-info/dependency_links.txt
alengen.egg-info/entry_points.txt
alengen.egg-info/not-zip-safe
alengen.egg-info/requires.txt
alengen.egg-info/top_level.txt