Metadata-Version: 1.1
Name: alengen
Version: 1.0.9
Summary: Automatic model code generator for SQLAlchemy
Home-page: https://github.com/massanchik/alengen
Author: Ashot Seropian
Author-email: ashot.seropyan@gmail.com
License: MIT
Keywords: sqlalchemy,alengen,generator,generate,autocode,entity,model
Platform: UNKNOWN
Classifier: Development Status :: 5 - Production/Stable
Classifier: Intended Audience :: Developers
Classifier: License :: OSI Approved :: MIT License
Classifier: Environment :: Console
Classifier: Topic :: Database
Classifier: Topic :: Software Development :: Code Generators
Classifier: Programming Language :: Python
Classifier: Programming Language :: Python :: 3
Classifier: Programming Language :: Python :: 3.2
Classifier: Programming Language :: Python :: 3.3
Classifier: Programming Language :: Python :: 3.4
